csgostats/__init__.py
csgotracker-0.0.3.dist-info/LICENSE
csgotracker-0.0.3.dist-info/METADATA
csgotracker-0.0.3.dist-info/WHEEL
csgotracker-0.0.3.dist-info/top_level.txt
csgotracker-0.0.3.dist-info/RECORD
