Metadata-Version: 2.1
Name: csgotracker
Version: 0.0.3
Summary: A basic tracker for Counter-Strike: Global Offensive stats
Author: doca
Author-email: docafavarato@gmail.com
Keywords: python,game,csgo,counter-strike,stats,tracker
Classifier: Development Status :: 1 - Planning
Classifier: Intended Audience :: Developers
Classifier: Programming Language :: Python :: 3
Classifier: Operating System :: OS Independent
License-File: LICENSE
Requires-Dist: requests
